{
    "BCN" : {
      "direct_flight": "True",
      "departure_date": "2017-11-13",
      "return_date": "2017-11-15",
      "departure": [{
          "departure_time": "time",
          "arrival_time": "time",
          "departure_airport": "airport_code",
          "arrival_airport": "airport_code",
          "airline": "airline"
          }
      ],
      "return": [{
          "departure_time": "time",
          "arrival_time": "time",
          "departure_airport": "airport_code",
          "arrival_airport": "airport_code",
          "airline": "airline"
          }
      ]
    }
}
